<?xml version="1.0" encoding="UTF-8"?>
<objects serializationModel="Studio.02.02.00">
	<object class="EncodingSetting" id="{fe0eadd2-a4c1-498c-9462-fe1d8b006529}">
		<property name="encodingFormat">
			<value>3</value>
		</property>
		<property name="quality">
			<value>37</value>
		</property>
		<relationship name="platform">
			<destination>{c9dd0206-beab-434f-baf8-bb81e8dfe751}</destination>
		</relationship>
		<relationship name="encodable">
			<destination>{c9dd0206-beab-434f-baf8-bb81e8dfe751}</destination>
		</relationship>
	</object>
</objects>
